README.md
setup.py
hehehaha/__init__.py
hehehaha/print_cwd.py
hehehaha/print_now.py
hehehaha.egg-info/PKG-INFO
hehehaha.egg-info/SOURCES.txt
hehehaha.egg-info/dependency_links.txt
hehehaha.egg-info/top_level.txt