Metadata-Version: 1.1
Name: hehehaha
Version: 1.0.1
Summary: my test
Home-page: https://github.com/XIHEHA/hehehaha
Author: CuiWeiming
Author-email: cuiweiming1110@163.com
License: GNU General Public License v3 (GPLv3)
Platform: all
Classifier: Development Status :: 4 - Beta
Classifier: Operating System :: OS Independent
Classifier: Intended Audience :: Developers
Classifier: License :: OSI Approved :: GNU General Public License v3 (GPLv3)
Classifier: Programming Language :: Python
Classifier: Programming Language :: Python :: Implementation
Classifier: Programming Language :: Python :: 3
Classifier: Programming Language :: Python :: 3.4
Classifier: Programming Language :: Python :: 3.5
Classifier: Programming Language :: Python :: 3.6
Classifier: Topic :: Software Development :: Libraries
